pressio4py/__init__.py
pressio4py/_p4pyimpl.cpython-37m-darwin.so
pressio4py/logger.py
pressio4py/ode.py
pressio4py/rom.py
pressio4py/solvers.py
pressio4py/apps/__init__.py
pressio4py/apps/advection_diffusion1d.py
pressio4py/apps/burgers1d.py
pressio4py/tests_compiled/test_ops_rank1_array.py
pressio4py/tests_compiled/test_ops_rank1_array_module.cpython-37m-darwin.so
pressio4py/tests_compiled/test_ops_rank2_array.py
pressio4py/tests_compiled/test_ops_rank2_array_module.cpython-37m-darwin.so
pressio4py-0.12.0.dist-info/LICENSE
pressio4py-0.12.0.dist-info/METADATA
pressio4py-0.12.0.dist-info/WHEEL
pressio4py-0.12.0.dist-info/top_level.txt
pressio4py-0.12.0.dist-info/RECORD
