Metadata-Version: 2.1
Name: pressio4py
Version: 0.12.0
Summary: pressio4py: projection-based model reduction for Python
Home-page: UNKNOWN
Author: F.Rizzi, E.Parish, P.Blonigan, J.Tencer
Author-email: fnrizzi@sandia.gov
License: UNKNOWN
Project-URL: Documentation, https://pressio.github.io/pressio4py/html/index.html
Project-URL: Source, https://github.com/Pressio/pressio4py
Keywords: model reduction,scientific computing,dense linear algebra,pressio,HPC
Platform: UNKNOWN
Classifier: License :: OSI Approved :: BSD License
Classifier: Operating System :: Unix
Classifier: Programming Language :: C++
Classifier: Programming Language :: Python :: 3 :: Only
Classifier: Topic :: Scientific/Engineering
Classifier: Topic :: Scientific/Engineering :: Mathematics
Classifier: Topic :: Scientific/Engineering :: Physics
Classifier: Topic :: Software Development :: Libraries
Classifier: Development Status :: 4 - Beta
Requires-Python: >=3
License-File: LICENSE
Requires-Dist: numpy
Requires-Dist: scipy
Requires-Dist: matplotlib
Requires-Dist: sklearn
